<?xml version="1.0" encoding="iso-8859-1" ?>
<newsitem itemid="142728" id="root" date="1996-10-25" xml:lang="en">
<title>USA: Global Intellicom buy ProNotes assets.</title>
<headline>Global Intellicom buy ProNotes assets.</headline>
<dateline>NEW YORK 1996-10-25</dateline>
<text>
<p>Global Intellicom Inc said Friday that it has acquired all assets of ProNotes Inc, a developer of speech recognition software and tools.</p>
<p>A company spokesman was not available to discuss terms of the transaction.</p>
</text>
<copyright>(c) Reuters Limited 1996</copyright>
<metadata>
<codes class="bip:countries:1.0">
  <code code="USA">
    <editdetail attribution="Reuters BIP Coding Group" action="confirmed" date="1996-10-25"/>
  </code>
</codes>
<codes class="bip:industries:1.0">
  <code code="I33020">
    <editdetail attribution="Reuters BIP Coding Group" action="confirmed" date="1996-10-25"/>
  </code>
  <code code="I3302021">
    <editdetail attribution="Reuters BIP Coding Group" action="confirmed" date="1996-10-25"/>
  </code>
</codes>
<codes class="bip:topics:1.0">
  <code code="C18">
    <editdetail attribution="Reuters BIP Coding Group" action="confirmed" date="1996-10-25"/>
  </code>
  <code code="C182">
    <editdetail attribution="Reuters BIP Coding Group" action="confirmed" date="1996-10-25"/>
  </code>
  <code code="CCAT">
    <editdetail attribution="Reuters BIP Coding Group" action="confirmed" date="1996-10-25"/>
  </code>
</codes>
<dc element="dc.date.created" value="1996-10-25"/>
<dc element="dc.publisher" value="Reuters Holdings Plc"/>
<dc element="dc.date.published" value="1996-10-25"/>
<dc element="dc.source" value="Reuters"/>
<dc element="dc.creator.location" value="NEW YORK"/>
<dc element="dc.creator.location.country.name" value="USA"/>
<dc element="dc.source" value="Reuters"/>
</metadata>
</newsitem>
