<?xml version="1.0" encoding="iso-8859-1" ?>
<newsitem itemid="162763" id="root" date="1996-11-04" xml:lang="en">
<title>USA: Check Point named in trademark suit.</title>
<headline>Check Point named in trademark suit.</headline>
<dateline>REDWOOD CITY, Calif 1996-11-04</dateline>
<text>
<p>Check Point Software Technologies Ltd said its Check Point Software Technologies Inc unit received a civil complaint by Checkpoint Systems Inc alleging trademark infringement and unfair competition due to use of the &quot;Check Point&quot; name.</p>
<p>Checkpoint Systems Inc principally makes theft prevention devices for retail stores.</p>
<p>Check Point Software Technologies, an inventor of stateful inspection architecture, said the claims are without merit and plans to vigorously defend against them.</p>
</text>
<copyright>(c) Reuters Limited 1996</copyright>
<metadata>
<codes class="bip:countries:1.0">
  <code code="USA">
    <editdetail attribution="Reuters BIP Coding Group" action="confirmed" date="1996-11-04"/>
  </code>
</codes>
<codes class="bip:industries:1.0">
  <code code="I33020">
    <editdetail attribution="Reuters BIP Coding Group" action="confirmed" date="1996-11-04"/>
  </code>
  <code code="I3302021">
    <editdetail attribution="Reuters BIP Coding Group" action="confirmed" date="1996-11-04"/>
  </code>
  <code code="I34420">
    <editdetail attribution="Reuters BIP Coding Group" action="confirmed" date="1996-11-04"/>
  </code>
</codes>
<codes class="bip:topics:1.0">
  <code code="C12">
    <editdetail attribution="Reuters BIP Coding Group" action="confirmed" date="1996-11-04"/>
  </code>
  <code code="CCAT">
    <editdetail attribution="Reuters BIP Coding Group" action="confirmed" date="1996-11-04"/>
  </code>
  <code code="GCAT">
    <editdetail attribution="Reuters BIP Coding Group" action="confirmed" date="1996-11-04"/>
  </code>
  <code code="GCRIM">
    <editdetail attribution="Reuters BIP Coding Group" action="confirmed" date="1996-11-04"/>
  </code>
</codes>
<dc element="dc.date.created" value="1996-11-04"/>
<dc element="dc.publisher" value="Reuters Holdings Plc"/>
<dc element="dc.date.published" value="1996-11-04"/>
<dc element="dc.source" value="Reuters"/>
<dc element="dc.creator.location" value="REDWOOD CITY, Calif"/>
<dc element="dc.creator.location.country.name" value="USA"/>
<dc element="dc.source" value="Reuters"/>
</metadata>
</newsitem>
