<?xml version="1.0" encoding="iso-8859-1" ?>
<newsitem itemid="190601" id="root" date="1996-11-14" xml:lang="en">
<title>JAPAN: Ines - 6mth parent results.</title>
<headline>Ines - 6mth parent results.</headline>
<dateline>TOKYO 1996-11-14</dateline>
<text>
<p>Six months to September 30, 1996</p>
<p> (Parent)	(in billions of yen unless specified)</p>
<p> Sales		 12.94		vs	   12.53</p>
<p> Operating	    1.30		vs	    1.05</p>
<p> Current		1.47		vs	    1.53</p>
<p> Net		  796    million	  vs	    1.59</p>
<p> EPS		   15.24 yen	  vs	   30.42 yen</p>
<p> Shares	     52 million	  vs	  52 million</p>
<p> Interim div	  3.00 yen	  vs	     nil</p>
<p>NOTE - Ines Corp is a data-processing firm.</p>
</text>
<copyright>(c) Reuters Limited 1996</copyright>
<metadata>
<codes class="bip:countries:1.0">
  <code code="JAP">
    <editdetail attribution="Reuters BIP Coding Group" action="confirmed" date="1996-11-14"/>
  </code>
</codes>
<codes class="bip:industries:1.0">
  <code code="I33020">
    <editdetail attribution="Reuters BIP Coding Group" action="confirmed" date="1996-11-14"/>
  </code>
  <code code="I3302020">
    <editdetail attribution="Reuters BIP Coding Group" action="confirmed" date="1996-11-14"/>
  </code>
</codes>
<codes class="bip:topics:1.0">
  <code code="C15">
    <editdetail attribution="Reuters BIP Coding Group" action="confirmed" date="1996-11-14"/>
  </code>
  <code code="C151">
    <editdetail attribution="Reuters BIP Coding Group" action="confirmed" date="1996-11-14"/>
  </code>
  <code code="CCAT">
    <editdetail attribution="Reuters BIP Coding Group" action="confirmed" date="1996-11-14"/>
  </code>
</codes>
<dc element="dc.date.created" value="1996-11-14"/>
<dc element="dc.publisher" value="Reuters Holdings Plc"/>
<dc element="dc.date.published" value="1996-11-14"/>
<dc element="dc.source" value="Reuters"/>
<dc element="dc.creator.location" value="TOKYO"/>
<dc element="dc.creator.location.country.name" value="JAPAN"/>
<dc element="dc.source" value="Reuters"/>
</metadata>
</newsitem>
