<?xml version="1.0" encoding="iso-8859-1" ?>
<newsitem itemid="245495" id="root" date="1996-12-10" xml:lang="en">
<title>USA: Microsoft unveils Internet Server software.</title>
<headline>Microsoft unveils Internet Server software.</headline>
<dateline>NEW YORK 1996-12-10</dateline>
<text>
<p>Microsoft Corp said Tuesday it plans to release this week its Microsoft Internet Information Server 3.0 software, a Web page development package.</p>
<p>Users of the Microsoft's NT Server network operating system 4.0 can download the software for free at the firm's Web site, they said.</p>
<p>-- New York Newsdesk +1 212 859 1610</p>
</text>
<copyright>(c) Reuters Limited 1996</copyright>
<metadata>
<codes class="bip:countries:1.0">
  <code code="USA">
    <editdetail attribution="Reuters BIP Coding Group" action="confirmed" date="1996-12-10"/>
  </code>
</codes>
<codes class="bip:industries:1.0">
  <code code="I33020">
    <editdetail attribution="Reuters BIP Coding Group" action="confirmed" date="1996-12-10"/>
  </code>
  <code code="I3302020">
    <editdetail attribution="Reuters BIP Coding Group" action="confirmed" date="1996-12-10"/>
  </code>
</codes>
<codes class="bip:topics:1.0">
  <code code="C22">
    <editdetail attribution="Reuters BIP Coding Group" action="confirmed" date="1996-12-10"/>
  </code>
  <code code="CCAT">
    <editdetail attribution="Reuters BIP Coding Group" action="confirmed" date="1996-12-10"/>
  </code>
</codes>
<dc element="dc.date.created" value="1996-12-10"/>
<dc element="dc.publisher" value="Reuters Holdings Plc"/>
<dc element="dc.date.published" value="1996-12-10"/>
<dc element="dc.source" value="Reuters"/>
<dc element="dc.creator.location" value="NEW YORK"/>
<dc element="dc.creator.location.country.name" value="USA"/>
<dc element="dc.source" value="Reuters"/>
</metadata>
</newsitem>
