<?xml version="1.0" encoding="iso-8859-1" ?>
<newsitem itemid="270697" id="root" date="1996-12-20" xml:lang="en">
<title>USA: Autodesk sweetens bid for Softdesk.</title>
<headline>Autodesk sweetens bid for Softdesk.</headline>
<dateline>SAN RAFAEL, Calif.</dateline>
<text>
<p>Autodesk Inc. has raised its takeover bid for Softdesk Inc. to $15 a share, or about $90 million, after a second, unidentified suitor made a competing proposal, the software companies said Friday.</p>
<p>Under the definitive agreement, Autodesk will pay the $15 a share in common stock based on the average closing prices for the five trading days before the closing date.</p>
<p>The companies had originally announced a price of $12 a share, or about $72 million, on Dec. 10.</p>
<p>Softdesk closed at $10.50, and Autodesk closed at $27.75 on Nasdaq on Thursday.</p>
<p>&quot;We have increased the purchase price principally in response to an indication of interest received by Softdesk from a third party,&quot; said Carol Bartz, Autodesk chairman and chief executive.</p>
<p>Dave Arnold, the chief executive of Softdesk, said the Henniker, N.H.-based company was committed to the Autodesk merger, which will be accounted for as a pooling of interests.</p>
<p>Softdesk, is a leading supplier of architecture, engineering and construction application software for professionals and consumers worldwide.</p>
<p>Autodesk, based in San Rafael, Calif., is a leading supplier of personal computer-based design software and PC multimedia tools.</p>
</text>
<copyright>(c) Reuters Limited 1996</copyright>
<metadata>
<codes class="bip:countries:1.0">
  <code code="USA">
    <editdetail attribution="Reuters BIP Coding Group" action="confirmed" date="1996-12-20"/>
  </code>
</codes>
<codes class="bip:industries:1.0">
  <code code="I33020">
    <editdetail attribution="Reuters BIP Coding Group" action="confirmed" date="1996-12-20"/>
  </code>
  <code code="I3302021">
    <editdetail attribution="Reuters BIP Coding Group" action="confirmed" date="1996-12-20"/>
  </code>
</codes>
<codes class="bip:topics:1.0">
  <code code="C18">
    <editdetail attribution="Reuters BIP Coding Group" action="confirmed" date="1996-12-20"/>
  </code>
  <code code="C181">
    <editdetail attribution="Reuters BIP Coding Group" action="confirmed" date="1996-12-20"/>
  </code>
  <code code="CCAT">
    <editdetail attribution="Reuters BIP Coding Group" action="confirmed" date="1996-12-20"/>
  </code>
</codes>
<dc element="dc.publisher" value="Reuters Holdings Plc"/>
<dc element="dc.date.published" value="1996-12-20"/>
<dc element="dc.source" value="Reuters"/>
<dc element="dc.creator.location" value="SAN RAFAEL, Calif."/>
<dc element="dc.creator.location.country.name" value="USA"/>
<dc element="dc.source" value="Reuters"/>
</metadata>
</newsitem>
