<?xml version="1.0" encoding="iso-8859-1" ?>
<newsitem itemid="294215" id="root" date="1997-01-08" xml:lang="en">
<title>USA: Netscape falls on downgrade--traders.</title>
<headline>Netscape falls on downgrade--traders.</headline>
<dateline>NEW YORK 1997-01-08</dateline>
<text>
<p>Netscape Communications Corp's stock price fell sharply early Wednesday in a selloff sparked by a downgrade by Deutsche Morgan Grenfell, traders said.</p>
<p>They said analyst William Gurley cut his recommendation on Netscape to accumulate from buy. Gurley's office declined comment. The change was based on valuation, among other factors, traders said.</p>
<p>In morning Nasdaq trade, Netscape was off 8-1/4 to 50-1/2, a decline of 14.5 percent. Almost three million shares traded in the first 40 minutes of the Nasdaq session -- double the average daily volume in the stock.  </p>
<p>A market maker in Netscape shares said Netscape closed yesterday at 58-3/8, near the analyst's price target of $60 per share.</p>
<p>In addition to valuation, the downgrade was also based on &quot;a lengthening sales cycle, a new pricing model and a major product transition,&quot; the market maker said.</p>
<p>&quot;But the fundamentals remain intact, though there is near-term uncertainty,&quot; he said.</p>
<p>The market maker quoted a DMG research note as saying, &quot;The fourth quarter is on track, but we think there is little chance of significant upside.&quot;</p>
<p>((-- Brendan Intindola, Wall Street Desk, 212-859-1734))</p>
</text>
<copyright>(c) Reuters Limited 1997</copyright>
<metadata>
<codes class="bip:countries:1.0">
  <code code="USA">
    <editdetail attribution="Reuters BIP Coding Group" action="confirmed" date="1997-01-08"/>
  </code>
</codes>
<codes class="bip:industries:1.0">
  <code code="I33020">
    <editdetail attribution="Reuters BIP Coding Group" action="confirmed" date="1997-01-08"/>
  </code>
  <code code="I3302021">
    <editdetail attribution="Reuters BIP Coding Group" action="confirmed" date="1997-01-08"/>
  </code>
</codes>
<codes class="bip:topics:1.0">
  <code code="C15">
    <editdetail attribution="Reuters BIP Coding Group" action="confirmed" date="1997-01-08"/>
  </code>
  <code code="C152">
    <editdetail attribution="Reuters BIP Coding Group" action="confirmed" date="1997-01-08"/>
  </code>
  <code code="CCAT">
    <editdetail attribution="Reuters BIP Coding Group" action="confirmed" date="1997-01-08"/>
  </code>
</codes>
<dc element="dc.date.created" value="1997-01-08"/>
<dc element="dc.publisher" value="Reuters Holdings Plc"/>
<dc element="dc.date.published" value="1997-01-08"/>
<dc element="dc.source" value="Reuters"/>
<dc element="dc.creator.location" value="NEW YORK"/>
<dc element="dc.creator.location.country.name" value="USA"/>
<dc element="dc.source" value="Reuters"/>
</metadata>
</newsitem>
