<?xml version="1.0" encoding="iso-8859-1" ?>
<newsitem itemid="95844" id="root" date="1996-10-04" xml:lang="en">
<title>USA: Halliburton Co completes acquisition.</title>
<headline>Halliburton Co completes acquisition.</headline>
<dateline>DALLAS 1996-10-04</dateline>
<text>
<p>Halliburton Co said Friday it completed its acquisition of Landmark Graphics Corp, whose shareholders approved the deal.</p>
<p>Halliburton is to issue 0.574 shares of its common stock for each outstanding share of Landmark common stock.</p>
<p>Based upon the shares outstanding on August 29, Halliburton will issue about 10.1 million shares of its common stock to Landmark shareholders. It also will reserve about 1.8 million shares that may be issued upon the exercise of Landmark stock options, the company said.  </p>
<p>Halliburton is an energy services, engineering, maintenance and construction company.</p>
</text>
<copyright>(c) Reuters Limited 1996</copyright>
<metadata>
<codes class="bip:countries:1.0">
  <code code="USA">
    <editdetail attribution="Reuters BIP Coding Group" action="confirmed" date="1996-10-04"/>
  </code>
</codes>
<codes class="bip:industries:1.0">
  <code code="I13000">
    <editdetail attribution="Reuters BIP Coding Group" action="confirmed" date="1996-10-04"/>
  </code>
  <code code="I33020">
    <editdetail attribution="Reuters BIP Coding Group" action="confirmed" date="1996-10-04"/>
  </code>
  <code code="I3302021">
    <editdetail attribution="Reuters BIP Coding Group" action="confirmed" date="1996-10-04"/>
  </code>
</codes>
<codes class="bip:topics:1.0">
  <code code="C18">
    <editdetail attribution="Reuters BIP Coding Group" action="confirmed" date="1996-10-04"/>
  </code>
  <code code="C181">
    <editdetail attribution="Reuters BIP Coding Group" action="confirmed" date="1996-10-04"/>
  </code>
  <code code="CCAT">
    <editdetail attribution="Reuters BIP Coding Group" action="confirmed" date="1996-10-04"/>
  </code>
</codes>
<dc element="dc.date.created" value="1996-10-04"/>
<dc element="dc.publisher" value="Reuters Holdings Plc"/>
<dc element="dc.date.published" value="1996-10-04"/>
<dc element="dc.source" value="Reuters"/>
<dc element="dc.creator.location" value="DALLAS"/>
<dc element="dc.creator.location.country.name" value="USA"/>
<dc element="dc.source" value="Reuters"/>
</metadata>
</newsitem>
